catscript/__init__.py
catscript/app.py
catscript/device.py
catscript/key.py
catscript/screen.py
catscript/script.py
catscript/sys.py
catscript/touch.py
catscript-1.5.0.dist-info/METADATA
catscript-1.5.0.dist-info/WHEEL
catscript-1.5.0.dist-info/licenses/LICENSE
catscript-1.5.0.dist-info/RECORD
